qagent/bot/demo/text_viz.py
qagent/executor/__init__.py
qagent/executor/base_executor.py
qagent/executor/extractors.py
qagent/executor/iter_filter.py
qagent/executor/llm_feeder.py
qagent/executor/llm_response.py
qagent/executor/response_to_data_binding.py
qagent/executor/response_validator.py
qagent/executor/simple_sequential_executor.py
qagent/llms/__init__.py
qagent/llms/base_lm.py
qagent/llms/openai/openai_gpt_lm.py
qagent/prompts/dialogflow/example-plan/network_to_ml.json
qagent/prompts/dialogflow/example-plan/table_analysis.json
qagent/prompts/dialogflow/example-plan/table_mod.json
qagent/prompts/dialogflow/example-plan/table_to_ml.json
qagent/prompts/dialogflow/example-plan/text-to-table.json
qagent/prompts/dialogflow/example-plan/text_mod.json
qagent/prompts/dialogflow/example-response/network_movie.json
qagent/prompts/dialogflow/example-response/network_movie_delta.json
qagent/prompts/libs/dummy-table.txt
qagent/prompts/libs/network-expand.txt
qagent/prompts/libs/table-column-partition.txt
qagent/prompts/libs/table-to-network.txt
qagent/prompts/libs/text-to-network.txt
qagent/prompts/libs/text-to-table-precheck.txt
qagent/prompts/libs/text-to-table.txt
qagent/prompts/prompt_giver.py
qagent/prompts/sys/error_prompts.py
qagent/query/__init__.py
qagent/query/core/__init__.py
qagent/query/core/llmprompt.py
qagent/query/core/queryplan.py
qagent/query/core/response_type.py
qagent/query/core/transition.py
qagent/query/utils/query_utils.py
qagent/query/utils/read_plan.py
qagent/taskgraph/__init__.py
qagent/taskgraph/basenode.py
qagent/taskgraph/fanout_task.py
qagent/taskgraph/llm_task.py
qagent/taskgraph/passthrough_task.py
qagent/taskgraph/rungraph.py
qagent/taskgraph/task_resp.py
qagent/udm/__init__.py
qagent/udm/base_schema.py
querai-0.1.9.dist-info/METADATA
querai-0.1.9.dist-info/WHEEL
querai-0.1.9.dist-info/RECORD
