Metadata-Version: 2.1
Name: querai
Version: 0.1.9
Summary: A middle layer between the applications and the LLMs.
License: BSD
Author: KL
Author-email: kun.lu.brain@gmail.com
Requires-Python: >=3.9,<4.0
Classifier: License :: Other/Proprietary License
Classifier: Programming Language :: Python :: 3
Classifier: Programming Language :: Python :: 3.9
Classifier: Programming Language :: Python :: 3.10
Classifier: Programming Language :: Python :: 3.11
Classifier: Programming Language :: Python :: 3.12
Requires-Dist: metavalidator (>=0.1.3,<0.2.0)
Requires-Dist: openai (>=1.35.5,<2.0.0)
Requires-Dist: pydantic (>=2.7.3,<3.0.0)
Requires-Dist: python-decouple (>=3.8,<4.0)
Requires-Dist: tenacity (>=8.3.0,<9.0.0)
